lafs_giab.py
setup.py
lafs_giab.egg-info/PKG-INFO
lafs_giab.egg-info/SOURCES.txt
lafs_giab.egg-info/dependency_links.txt
lafs_giab.egg-info/requires.txt
lafs_giab.egg-info/top_level.txt