Metadata-Version: 1.0
Name: lafs-giab
Version: 0.1
Summary: Configure/start/stop a self-contained Tahoe-LAFS grid.
Home-page: https://github.com/nejucomo/lafs-giab
Author: Nathan Wilcox
Author-email: nejucomo@gmail.com
License: GPLv3
Platform: UNKNOWN
